{
  "title": "Markov Decision Processes",
  "content": "<b>Markov Decision Processes</b> <span style=\"color:#A3F7BF\">Markov Decision Processes</span> is a fundamental topic that encompasses key principles and practical applications. In this lesson, we explore the core concepts behind Markov Decision Processes, including its definition, historical background, and real-world examples. Understanding Markov Decision Processes requires examining its theoretical foundations as well as how it is applied in various domains. Throughout this content, you will learn about the significance of Markov Decision Processes in modern contexts and why it matters for both academic study and professional practice. The lesson will delve into the methodologies associated with Markov Decision Processes, highlighting essential techniques and best practices. By the end of this lesson, you should be able to explain what Markov Decision Processes entails and how it contributes to broader subject areas. Applications of Markov Decision Processes are diverse, spanning from introductory use cases to advanced scenarios that push the boundaries of current knowledge. We will also cover common challenges and pitfalls when working with Markov Decision Processes, along with strategies to overcome them. Examples provided in this lesson will illustrate how Markov Decision Processes interacts with related topics and how it supports more complex workflows. As you engage with exercises and examples, you will develop a deeper appreciation for the role of Markov Decision Processes in contemporary study and practice. Throughout the explanations, key terms will be highlighted to help reinforce your comprehension of Markov Decision Processes. The lesson content is structured to guide you from foundational aspects to more nuanced considerations related to",
  "quiz": [
    {
      "question": "Which statement best describes Markov Decision Processes?",
      "options": [
        "It is a technique that involves understanding and applying key principles.",
        "It is a method that has no practical use.",
        "It refers solely to hardware implementation.",
        "It is exclusively theoretical with no real-world examples."
      ],
      "answer": 0
    },
    {
      "question": "What is a key benefit of learning about Markov Decision Processes?",
      "options": [
        "It enhances your ability to apply concepts in practical situations.",
        "It guarantees success in all fields without further study.",
        "It replaces the need for foundational knowledge.",
        "It is unrelated to professional practice."
      ],
      "answer": 0
    },
    {
      "question": "In which domain would you most likely encounter Markov Decision Processes?",
      "options": [
        "In fields related to its theoretical and practical applications.",
        "In ancient history unrelated to modern contexts.",
        "In unrelated arts without technical relevance.",
        "In contexts that do not require any analysis."
      ],
      "answer": 0
    }
  ]
}